README.md
setup.py
datacommon/__init__.py
datacommon/constants.py
datacommon/dataSet.py
datacommon/functionManager.py
datacommon/reader.py
datacommon/udfs.py
datacommon/util.py
datacommon.egg-info/PKG-INFO
datacommon.egg-info/SOURCES.txt
datacommon.egg-info/dependency_links.txt
datacommon.egg-info/requires.txt
datacommon.egg-info/top_level.txt